rim/__init__.py
rim/definitions.py
rim/rim.py
rim/utils.py
rim/architectures/__init__.py
rim/architectures/base.py
rim/architectures/hourglass.py
rim/architectures/unet.py
rim/layers/__init__.py
rim/layers/gru.py
rim/layers/gru_component.py
torch_rim-0.2.9.dist-info/LICENSE.txt
torch_rim-0.2.9.dist-info/METADATA
torch_rim-0.2.9.dist-info/WHEEL
torch_rim-0.2.9.dist-info/top_level.txt
torch_rim-0.2.9.dist-info/RECORD
